{"commits_dict": {"Eliezer": 4, "Mitar": 27, "Oleksandr Chekhovskyi": 1, "Scott Brenner": 1, "Hugh Willson": 20, "Joshua Ohlman": 1, "dr-dimitru": 11, "David Glasser": 15, "Ben Newman": 1321, "Jesse Rosenberger": 64, "brucejo": 1, "Sashko Stubailo": 52, "Zoltan Olah": 75, "Tom Coleman": 271, "Geoffrey Booth": 16, "Alex Terpyakov": 1, "Rhywden": 1, "P\u00e9ter P\u00e1l Koszta": 3, "David Burles": 10, "Seba Kerckhof": 7, "choyweston": 6, "Mehdi AHRAOUI": 2, "Joshua Byrd": 2, "laosb": 9, "Wexpo Lyu": 39, "Denis Davidyuk": 1, "Lucas Hansen": 2, "Thea Lamkin": 4, "Christian Klaussner": 8, "Devin Bayer": 1, "Michael Oberegger": 2, "dhrubins": 1, "Ramez Rafla": 1, "c9s": 7, "lucfranken": 5, "Rishabh Singhal": 2, "Martijn Walraven": 147, "Rodrigo Palhares": 1, "Michiel ter Reehorst": 1, "Lieuwe Rooijakkers": 2, "seke": 5, "Mehdi Ahraoui": 2, "Gabriel Engel": 1, "Brian Lukoff": 1, "gsaynac": 1, "Michael Mason": 2, "Andy Edwards": 2, "Pradel Le\u0301o": 4, "Dirk Stolle": 1, "Matthijs Brobbel": 1, "Yo-An Lin": 2, "Maxime Quandalle": 3, "Benedikt Huss": 1, "Guillaume Sabran": 1, "Birk Skyum": 2, "Alon Amster": 4, "dr.dimitru": 1, "Dotan Simha": 5, "Raghavendra Rachamadugu": 4, "Loren Sands-Ramshaw": 2, "Eli Skeggs": 1, "Ilari Patrikka": 1, "Tom Freudenberg": 3, "Gabriel Rubens": 3, "Fabricio Nascimento": 14, "Nathan Muir": 11, "Tomas Brambora": 3, "Workflow": 1, "Jack Ivy": 1, "Jonas Aschenbrenner": 1, "Hongbo Miao": 1, "Jacob Weisz": 3, "Peter Mooney": 3, "chemicstry": 1, "Gadi Cohen": 3, "Jesper We": 1, "Mitchell Wulfman": 1, "Andrew Wilcox": 2, "Eric Dobbertin": 5, "gsuess": 1, "Michael Cole": 2, "Dean Radcliffe": 1, "Nuvi": 3, "Alexander Sulfrian": 1, "William Oliveira": 1, "Marcelo Schmidt": 2, "Dan Ryan": 1, "skirunman": 4, "Jamie Loberman": 1, "Daniel Klischies": 2, "hwillson": 2, "Skaag Argonius": 1, "Michel Floyd": 1, "Joseph Orbegoso Pea": 2, "emgee3": 2, "Tarun Batra": 1, "Maciej Tre\u0328bacz": 2, "Eric Wyne": 1, "Rahul": 1, "Woo Jin": 1, "Sarah A": 3, "Andr\u00e9 Ericson": 1, "Matt McCutchen": 1, "Avital Oliver": 36, "Lewis Wright": 1, "Adam Monsen": 1, "SEKE": 2, "Nick Martin": 2, "Brian Engelhardt": 1, "Robert Dickert": 2, "Fabien Blanchard": 1, "Josh Owens": 4, "David Greenspan": 39, "ozsayag": 1, "lassombra": 1, "Evan Marsland": 1, "Prayag Verma": 1, "Simon Fridlund": 1, "Steven Edouard": 5, "nagelflorian": 1, "Sheel Patel": 2, "Doug Horner": 1, "Braden Whitten": 1, "Ieuan Griffiths": 1}, "additions_dict": {"Eliezer": 7, "Mitar": 20131, "Oleksandr Chekhovskyi": 16, "Scott Brenner": 1, "Hugh Willson": 476, "Joshua Ohlman": 0, "dr-dimitru": 25201, "David Glasser": 314, "Ben Newman": 158882, "Jesse Rosenberger": 1313, "brucejo": 2, "Sashko Stubailo": 926, "Zoltan Olah": 1447, "Tom Coleman": 30537, "Geoffrey Booth": 482, "Alex Terpyakov": 2, "Rhywden": 1, "P\u00e9ter P\u00e1l Koszta": 103, "David Burles": 182, "Seba Kerckhof": 216, "choyweston": 61, "Mehdi AHRAOUI": 1184, "Joshua Byrd": 2, "laosb": 135, "Wexpo Lyu": 1692, "Denis Davidyuk": 1, "Lucas Hansen": 6, "Thea Lamkin": 166, "Christian Klaussner": 125, "Devin Bayer": 45, "Michael Oberegger": 63, "dhrubins": 17, "Ramez Rafla": 1, "c9s": 71, "lucfranken": 40, "Rishabh Singhal": 166, "Martijn Walraven": 9494, "Rodrigo Palhares": 12, "Michiel ter Reehorst": 1, "Lieuwe Rooijakkers": 4, "seke": 19, "Mehdi Ahraoui": 131, "Gabriel Engel": 9, "Brian Lukoff": 2, "gsaynac": 1, "Michael Mason": 3, "Andy Edwards": 589, "Pradel Le\u0301o": 395, "Dirk Stolle": 1, "Matthijs Brobbel": 1, "Yo-An Lin": 12, "Maxime Quandalle": 78, "Benedikt Huss": 122, "Guillaume Sabran": 10, "Birk Skyum": 1, "Alon Amster": 57, "dr.dimitru": 1, "Dotan Simha": 9, "Raghavendra Rachamadugu": 50, "Loren Sands-Ramshaw": 10, "Eli Skeggs": 6, "Ilari Patrikka": 0, "Tom Freudenberg": 9, "Gabriel Rubens": 71, "Fabricio Nascimento": 324, "Nathan Muir": 89, "Tomas Brambora": 5, "Workflow": 1, "Jack Ivy": 7, "Jonas Aschenbrenner": 5, "Hongbo Miao": 2, "Jacob Weisz": 18, "Peter Mooney": 92, "chemicstry": 96, "Gadi Cohen": 150, "Jesper We": 1, "Mitchell Wulfman": 4, "Andrew Wilcox": 3, "Eric Dobbertin": 145, "gsuess": 25, "Michael Cole": 3, "Dean Radcliffe": 74, "Nuvi": 14, "Alexander Sulfrian": 23, "William Oliveira": 2, "Marcelo Schmidt": 11, "Dan Ryan": 31, "skirunman": 73, "Jamie Loberman": 0, "Daniel Klischies": 2, "hwillson": 2, "Skaag Argonius": 11, "Michel Floyd": 11, "Joseph Orbegoso Pea": 5, "emgee3": 6, "Tarun Batra": 1, "Maciej Tre\u0328bacz": 6, "Eric Wyne": 1, "Rahul": 1, "Woo Jin": 2, "Sarah A": 3, "Andr\u00e9 Ericson": 10, "Matt McCutchen": 9, "Avital Oliver": 9207, "Lewis Wright": 27, "Adam Monsen": 1, "SEKE": 72, "Nick Martin": 20, "Brian Engelhardt": 166, "Robert Dickert": 2, "Fabien Blanchard": 2, "Josh Owens": 18, "David Greenspan": 2048, "ozsayag": 7, "lassombra": 1, "Evan Marsland": 13, "Prayag Verma": 1, "Simon Fridlund": 0, "Steven Edouard": 34, "nagelflorian": 11, "Sheel Patel": 2, "Doug Horner": 2, "Braden Whitten": 1, "Ieuan Griffiths": 1}, "deletions_dict": {"Eliezer": 3, "Mitar": 26902, "Oleksandr Chekhovskyi": 12, "Scott Brenner": 1, "Hugh Willson": 74, "Joshua Ohlman": 3, "dr-dimitru": 29283, "David Glasser": 4169, "Ben Newman": 169369, "Jesse Rosenberger": 420, "brucejo": 2, "Sashko Stubailo": 1438, "Zoltan Olah": 1086, "Tom Coleman": 119486, "Geoffrey Booth": 230, "Alex Terpyakov": 2, "Rhywden": 1, "P\u00e9ter P\u00e1l Koszta": 7, "David Burles": 240, "Seba Kerckhof": 41, "choyweston": 9, "Mehdi AHRAOUI": 22, "Joshua Byrd": 2, "laosb": 81, "Wexpo Lyu": 972, "Denis Davidyuk": 12, "Lucas Hansen": 14, "Thea Lamkin": 18, "Christian Klaussner": 42, "Devin Bayer": 2, "Michael Oberegger": 51, "dhrubins": 10, "Ramez Rafla": 1, "c9s": 35, "lucfranken": 18, "Rishabh Singhal": 21, "Martijn Walraven": 5068, "Rodrigo Palhares": 2, "Michiel ter Reehorst": 1, "Lieuwe Rooijakkers": 4, "seke": 19, "Mehdi Ahraoui": 43, "Gabriel Engel": 0, "Brian Lukoff": 2, "gsaynac": 1, "Michael Mason": 2, "Andy Edwards": 25368, "Pradel Le\u0301o": 9, "Dirk Stolle": 1, "Matthijs Brobbel": 1, "Yo-An Lin": 2, "Maxime Quandalle": 40, "Benedikt Huss": 1, "Guillaume Sabran": 8, "Birk Skyum": 4, "Alon Amster": 5, "dr.dimitru": 1, "Dotan Simha": 3, "Raghavendra Rachamadugu": 17, "Loren Sands-Ramshaw": 1, "Eli Skeggs": 0, "Ilari Patrikka": 12, "Tom Freudenberg": 8, "Gabriel Rubens": 16, "Fabricio Nascimento": 109, "Nathan Muir": 59, "Tomas Brambora": 5, "Workflow": 1, "Jack Ivy": 0, "Jonas Aschenbrenner": 225, "Hongbo Miao": 2, "Jacob Weisz": 5, "Peter Mooney": 0, "chemicstry": 60, "Gadi Cohen": 19, "Jesper We": 1, "Mitchell Wulfman": 4, "Andrew Wilcox": 3, "Eric Dobbertin": 54, "gsuess": 1, "Michael Cole": 3, "Dean Radcliffe": 0, "Nuvi": 4, "Alexander Sulfrian": 1, "William Oliveira": 2, "Marcelo Schmidt": 8, "Dan Ryan": 1, "skirunman": 5, "Jamie Loberman": 1, "Daniel Klischies": 2, "hwillson": 0, "Skaag Argonius": 3, "Michel Floyd": 13, "Joseph Orbegoso Pea": 5, "emgee3": 6, "Tarun Batra": 1, "Maciej Tre\u0328bacz": 1, "Eric Wyne": 1, "Rahul": 1, "Woo Jin": 2, "Sarah A": 3, "Andr\u00e9 Ericson": 10, "Matt McCutchen": 0, "Avital Oliver": 27413, "Lewis Wright": 4, "Adam Monsen": 1, "SEKE": 36, "Nick Martin": 10, "Brian Engelhardt": 38, "Robert Dickert": 2, "Fabien Blanchard": 4, "Josh Owens": 7, "David Greenspan": 1118, "ozsayag": 3, "lassombra": 1, "Evan Marsland": 1, "Prayag Verma": 1, "Simon Fridlund": 5, "Steven Edouard": 17, "nagelflorian": 0, "Sheel Patel": 2, "Doug Horner": 1, "Braden Whitten": 1, "Ieuan Griffiths": 1}}