{"nathanleclaire": 4, "runcom": 22, "sharenz": 1, "StefanScherer": 2, "piontec": 2, "briceburg": 1, "rmb938": 2, "allencloud": 3, "thaJeztah": 41, "weekface": 1, "lightsea90": 1, "mavenugo": 2, "mrburrito": 1, "joeshaw": 1, "AdamBouhmad": 1, "AkihiroSuda": 6, "amyangfei": 1, "liyaka": 2, "realityone": 1, "coolljt0725": 11, "jhowardmsft": 7, "jpetazzo": 2, "migueldemiguel": 1, "yuewko": 1, "Bekt": 1, "jaredcnance": 1, "bvis": 2, "srust": 3, "ndegory": 1, "justincormack": 4, "sign2k": 1, "Dennor": 1, "yank1": 2, "djs55": 1, "JamesJJ": 4, "tonistiigi": 12, "nilsotto": 1, "techninja1008": 1, "albers": 4, "scottstensland": 1, "yashgt": 1, "boskiv": 1, "friism": 5, "aaronlehmann": 7, "dmyerscough": 1, "manoj0077": 1, "wrfly": 1, "mstanleyjones": 1, "cpuguy83": 9, "pcgeek86": 4, "twang2218": 2, "phyllisstein": 1, "andrewslotin": 1, "kharpMSFT": 1, "hubo1016": 1, "presidento": 1, "wsong": 1, "terje2001": 1, "Renay": 1, "KevinTHU": 1, "SpComb": 1, "vikstrous": 13, "mskarbek": 1, "adaphi": 2, "tomdee": 1, "sblackstone": 1, "kleptog": 1, "clarity99": 1, "fruetschi": 1, "tianon": 3, "tophj-ibm": 2, "cucyzrd": 1, "erikh": 2, "fuentecilla86": 1, "feedthefire": 1, "ThomasSteinbach": 1, "tombooth": 1, "derfred": 1, "ghost": 2, "dhiltgen": 9, "TheBeeMan": 1, "hmdhasani": 1, "rs38": 1, "leth": 1, "jdfless": 1, "samuelkarp": 1, "tswift242": 3, "DEVELByte": 1, "a-ba": 1, "ionfist": 1, "pascalandy": 1, "vitan": 1, "jefflill": 1, "vielmetti": 1, "newnius": 1, "tevjef": 1, "shane-axiom": 1, "MohammedYunus": 1, "ncdc": 1, "Murf": 1, "m4h3": 1, "foxylion": 1, "lbguilherme": 1, "kaithar": 1, "ManoMarks": 1, "shaloulcy": 1, "berndtj": 1, "rogaha": 4, "soanni": 1, "edwintorok": 1, "k2xl": 1, "dangreen": 1, "fabiendibot": 1, "codeb2cc": 1, "stepanv": 1, "belovanton": 1, "deviantony": 1, "jaylinski": 1, "anokun7": 1, "burdiyan": 1, "Khazrak": 1, "evanp": 2, "mrjana": 2, "Anvil": 1, "ibuildthecloud": 13, "sap1ens": 1, "dangra": 1, "ascora": 1, "saiwl": 1, "dnephin": 4, "nyanloutre": 1, "bweston92": 1, "LK4D4": 3, "samber": 2, "pmcq": 1, "dnwake": 1, "s-yata": 1, "pvnovarese": 1, "tibkiss": 1, "pho": 1, "freeseacher": 1, "gg7": 1, "shishir-a412ed": 5, "BrickXu": 1, "CrimsonGlory": 1, "urlund": 1, "damozhiying": 1, "tiaanl": 1, "lixiaobing10051267": 1, "ypjin": 2, "manixx": 1, "matt-richardson": 1, "sayash": 1, "jonathonl": 1, "zjxpsetp": 1, "indygreg": 1, "realcr": 1, "Flow86": 1, "Caligatio": 1, "dimw": 1, "nitinmidha": 1, "fermayo": 1, "yosifkit": 1, "speier": 1, "jamesongithub": 1, "fernandoacorreia": 1, "rkeilty": 1, "piotrb": 1, "easeway": 1, "akamalov": 1, "perigee": 1, "swernli": 1, "Furdarius": 1, "mvsestito": 1, "CRTX": 1, "langdead": 1, "b0ch3nski": 1, "sqleejan": 1, "xytis": 1, "duttski": 1, "MatthewMiele": 1, "dariko": 2, "abronan": 5, "hvpareja": 1, "pablitok": 1, "greggilbert": 1, "raesene": 1, "michael-holzheu": 1, "sfsmithcha": 1, "osallou": 1, "Noodle05": 2, "stevvooe": 5, "bboreham": 3, "sebi-hgdata": 8, "mike-hearn": 1, "gorazio": 1, "jprellberg": 1, "crosbymichael": 2, "jhorwit2": 4, "aaithal": 1, "govint": 1, "mbentley": 3, "GuillaumeDerval": 2, "paralin": 1, "mikkotikkanen": 1, "rosteroster": 1, "Quentinvarquet": 1, "Stehsegler": 2, "estesp": 4, "brauner": 1, "vnpavanelli": 1, "mgoelzer": 4, "sweekarp": 1, "jgarcia-mesosphere": 1, "ligc": 2, "nkovacs": 2, "benheilers": 1, "sentientmonkey": 1, "mrunalp": 1, "bennetimo": 1, "jerbia": 1, "anusha-ragunathan": 1, "telphan": 1, "moqmar": 1, "mprivat": 1, "tombee": 1, "clnperez": 1, "felixsanz": 1, "zuhouhu": 1, "r0c": 1, "netroby": 1, "rvernica": 1, "dmcgowan": 1, "aanand": 2, "johker01": 1, "adamjk-dev": 1, "jimmidyson": 1, "jyrkiput": 1, "ptptptptptpt": 1, "lukeck": 1, "sdemura": 1, "saada": 1, "mnottale": 2, "wjimenez5271": 1, "BenHall": 3, "jorge07": 1, "AlexOugh": 1, "jnoller": 2, "provegard": 1, "dgageot": 2, "lheckemann": 2, "ijc25": 1, "yomimono": 1, "aboch": 1, "andyneff": 1, "bigeagle": 1, "marcelmfs": 1, "stefanfoulis": 1, "rohitjaini": 1, "volak": 1, "liucw2012": 1, "brian-bason": 1, "mlecar": 1, "akshaymoghe": 1, "jizhilong": 1, "chiptip": 1, "brandonstevens": 1, "jessfraz": 1, "maratkomarov": 2, "PatrickLang": 1, "boucher": 1, "slank": 1, "agyanttiwari": 1, "kunalkushwaha": 1, "anthonychu": 1, "lauraglasu": 1, "ggerbaud": 1, "sanmai-NL": 2, "vitia": 1, "onursoyer": 1, "duglin": 2, "saintdev": 1, "akaey": 1, "CVTJNII": 1, "relistan": 1, "mkocikowski": 1, "BediarSofiane": 1, "lblackstone": 1, "CodingFabian": 1, "amit-gshe": 1, "AndreKR": 1, "noidi": 1, "pcarrier": 3, "tiborvass": 3, "vpaul": 1, "talon-hartmann": 1, "Teudimundo": 1, "chefarov": 1, "nazar-pc": 1, "fkautz": 1, "jimbobhickville": 1, "priestlyemu": 1, "Silex": 1, "byrnedo": 1, "PierreF": 1, "jordic": 1, "x3ro": 1, "pstauffer": 1, "frostynova": 1, "djtm": 1, "rade": 1, "alex3d": 1, "akalipetis": 1, "mindaugasrukas": 1, "danielhoherd": 1, "mathiasconradt": 1, "rhuss": 1, "insertinterestingnamehere": 1, "Garreat": 1, "RomanSaveljev": 1, "isavcic": 1, "vdemeester": 1, "kencochrane": 1, "dvic": 1, "calavera": 1, "jordmoz": 1, "abilash222": 1, "embray": 1, "yongtang": 1, "Soulou": 4, "netvl": 2, "dpgeekzero": 1, "marcellodesales": 1, "zunayed": 2, "amitkris": 1, "cyphar": 2, "darnells": 2, "talex5": 1, "polonskiy": 2, "S-YOU": 1, "AlekseyMartynov": 1, "nikolaiderzhak": 1, "neotysit": 1, "dohnto": 1, "dato": 1, "felixSchl": 1, "novsh": 1, "KostyaSha": 1, "icecrime": 1, "Salmondx": 1, "dmp1ce": 1, "skohanim": 2, "pietv": 1, "mountkin": 1, "ColinHebert": 2, "tlunter": 1, "clintonskitson": 1, "kelemen": 1, "gionn": 1, "dmp42": 2, "luqmanshareef": 1, "mpiermar": 1, "rutsky": 1, "adbrowne": 1, "ozlerhakan": 2, "micahhausler": 1, "JoelJ": 1, "bobrik": 1, "realulim": 1, "tizzo": 1, "aalexand": 1, "mikedougherty": 1, "ezrasilvera": 1, "jianghaitao": 1, "zoell": 1, "leejansq": 2, "kravietz": 1, "awh": 1, "rawouter": 1, "michaelsauter": 1, "dqminh": 1, "stund": 1, "chosenken": 1, "superdump": 1, "wp0pw": 1, "astopy": 1, "HackToday": 1, "patrickbcullen": 1, "mmicael1": 1, "larskanis": 1, "cdanielw": 1, "guoshimin": 1, "qq690388648": 1, "vdavy": 1, "digitaldavenyc": 1, "lox": 1, "necto": 1, "dongluochen": 1, "jmhale": 1, "linlinlinlin": 1, "bjaglin": 1, "jake-low": 1, "oszi": 1, "jredl-va": 1, "libscott": 1, "Chili-Man": 1, "Miguel-Fontes": 1, "miquella": 1, "tjdett": 1, "askb": 1, "venkatramachandran": 1, "delfuego": 1, "follesoe": 1, "stefanleh": 1, "lukemarsden": 1, "jgkamat": 1, "rhatdan": 1, "BrianBland": 1, "sdurrheimer": 1, "amluto": 1, "allamand": 1, "riklaunim": 1, "pooya": 1, "sconts": 1, "ankushagarwal": 1, "mcieslik-mctp": 1, "alvinr": 1, "mhrivnak": 1, "jeremyeder": 1, "frioux": 1, "phanimahesh": 1, "CGavrila": 1, "scottdraves": 1, "borntorock": 1, "sheavner": 1, "meeee": 1, "imehrdad2012": 1, "agunnerson-ibm": 1, "kroeliebuschie": 1, "yanchenw": 1, "stuartpb": 2, "nkwangleiGIT": 1, "sschepens": 1, "jgadling": 1, "garrickp": 1, "gissehel": 1, "jongiddy": 1, "briangough": 1, "jgautheron": 1, "alexeyfrank": 1, "ernetas": 1, "Luzifer": 1, "vincentwoo": 1, "pbecotte": 1, "elrac": 1, "nomeata": 1, "lvangool": 1, "corradio": 1, "vbatts": 1, "analytically": 1, "jagan-veeraraghavan": 1, "stumpyfr": 1, "emsi": 1, "FossiFoo": 1, "witlessbird": 1, "shin-": 1, "deiga": 1, "discordianfish": 3, "damm": 1, "phemmer": 1, "dbabits": 1, "overplumbum": 1, "jrnos": 1, "e-max": 1, "sthulb": 1, "tnachen": 1, "dfarrell07": 1, "UnderGreen": 1, "tonicbupt": 1, "ericpromislow": 1, "jakedt": 1, "pditommaso": 1, "Attil": 1, "wiliamsouza": 1, "harshavardhana": 1, "hanwoody": 1, "vieira": 1, "iwinux": 1, "ConradIrwin": 1, "unclejack": 1, "ekle": 1, "polvi": 1, "poe": 1, "tavisrudd": 1, "AaronFriel": 1, "marklit": 1, "astraw": 1}